[
  {
    "id": "vm-aabningskamp",
    "type": "internal",
    "icon": "⚽",
    "title": "VM – Åbningskamp",
    "subtitle": "Mexico – Sydafrika",
    "date": "2026-06-11",
    "start": "20:00",
    "end": "23:30",
    "timeText": "Dørene åbner kl. 20.00 · Kampstart kl. 21.00",
    "place": "Logen, Frederiksgade 15, Slagelse",
    "poster": "assets/vm-aabningskamp-2026.png",
    "text": "Uformel fodboldaften med kamp på storskærm, chips, hygge og mulighed for at købe øl og vand i baren. Tag gerne en ledsager med."
  },
  {
    "id": "vm-gruppekamp",
    "type": "internal",
    "icon": "⚽",
    "title": "VM – Gruppekamp",
    "subtitle": "Norge – Frankrig",
    "date": "2026-06-26",
    "start": "20:00",
    "end": "23:30",
    "timeText": "Dørene åbner kl. 20.00 · Kampstart kl. 21.00",
    "place": "Logen, Frederiksgade 15, Slagelse",
    "poster": "assets/vm-gruppekamp-2026.png",
    "text": "Endnu en uformel VM-aften i logen med storskærm, chips og god stemning. Øl og vand kan købes i baren."
  },
  {
    "id": "vm-finale",
    "type": "internal",
    "icon": "⚽",
    "title": "VM – Finale",
    "subtitle": "Finaleaften i logen",
    "date": "2026-07-19",
    "start": "20:00",
    "end": "23:59",
    "timeText": "Dørene åbner kl. 20.00 · Kampstart kl. 21.00",
    "place": "Logen, Frederiksgade 15, Slagelse",
    "poster": "assets/vm-finale-2026.png",
    "text": "Finaleaften i logen med storskærm, chips og hygge. Øl og vand kan købes i baren. Tag gerne en ledsager med."
  },
  {
    "id": "loppemarked",
    "type": "public",
    "icon": "🛍️",
    "title": "Loppemarked",
    "subtitle": "Kom og gør et kup",
    "date": "2026-08-22",
    "start": "10:00",
    "end": "15:00",
    "timeText": "Kl. 10.00 – 15.00",
    "place": "Odd Fellow Bygningen, Frederiksgade 15, Slagelse",
    "poster": "assets/loppemarked-2026.png",
    "text": "Loppemarked i Odd Fellow-huset med stande, loppefund, pølser med brød, kaffe, kage og gratis popcorn."
  },
  {
    "id": "sct-michaels-nat",
    "type": "public",
    "icon": "🎪",
    "title": "Sct. Michaels Nat",
    "subtitle": "Mød Odd Fellow logerne i Slagelse",
    "date": "2026-09-25",
    "start": "18:00",
    "end": "22:00",
    "timeText": "Fredag d. 25. september",
    "place": "Slagelse Midtby",
    "poster": "assets/sct-michaels-nat-2026.png",
    "text": "Kom forbi vores stand og få en uforpligtende snak om fællesskab, aktiviteter og hvad der foregår i en loge. Der vil også være mulighed for at vinde præmier."
  },
  {
    "id": "sct-patricks-day",
    "type": "public",
    "icon": "🍀",
    "title": "Sct. Patrick's Day",
    "subtitle": "Vi gentager succesen",
    "date": "2027-03-19",
    "start": "17:00",
    "end": "23:00",
    "timeText": "Kl. 17.00 – 23.00",
    "place": "Odd Fellow Bygningen, Frederiksgade 15, Slagelse",
    "poster": "assets/sct-patricks-day-2027.png",
    "text": "Festlig aften med musik, fællesskab, irsk stemning, salg af drikkevarer og mulighed for at købe lidt mad."
  },
  {
    "id": "sommerudflugt-2026",
    "type": "internal",
    "icon": "🚋",
    "title": "Sommerudflugt 2026",
    "subtitle": "Sporvejsmuseet Skjoldenæsholm",
    "date": "2026-07-25",
    "start": "10:30",
    "end": "16:00",
    "timeText": "Mødetid kl. 10.30 på parkeringspladsen",
    "place": "Skjoldenæsvej 95, 4174 Jystrup",
    "poster": "assets/sommerudflugt-2026.jpg",
    "text": "Sommerudflugt til Sporvejsmuseet Skjoldenæsholm. Fælles frokost kl. 12.00 med smørrebrød, kaffe og kage. Pris 250 kr. pr. person. Tilmelding og betaling senest 19. juli til Torben Møller Sørensen."
  }
]